LICENSE.md
MANIFEST.in
README.rst
setup.py
src/waldur_cost_planning/__init__.py
src/waldur_cost_planning/admin.py
src/waldur_cost_planning/apps.py
src/waldur_cost_planning/extension.py
src/waldur_cost_planning/filters.py
src/waldur_cost_planning/models.py
src/waldur_cost_planning/optimizers.py
src/waldur_cost_planning/register.py
src/waldur_cost_planning/serializers.py
src/waldur_cost_planning/urls.py
src/waldur_cost_planning/views.py
src/waldur_cost_planning.egg-info/PKG-INFO
src/waldur_cost_planning.egg-info/SOURCES.txt
src/waldur_cost_planning.egg-info/dependency_links.txt
src/waldur_cost_planning.egg-info/entry_points.txt
src/waldur_cost_planning.egg-info/not-zip-safe
src/waldur_cost_planning.egg-info/requires.txt
src/waldur_cost_planning.egg-info/top_level.txt
src/waldur_cost_planning/migrations/0001_initial.py
src/waldur_cost_planning/migrations/__init__.py
src/waldur_cost_planning/plugins/__init__.py
src/waldur_cost_planning/plugins/aws.py
src/waldur_cost_planning/plugins/azure.py
src/waldur_cost_planning/plugins/digitalocean.py
src/waldur_cost_planning/plugins/openstack_tenant.py
src/waldur_cost_planning/plugins/utils.py
src/waldur_cost_planning/templates/waldur_cost_planning/report.html
src/waldur_cost_planning/tests/__init__.py
src/waldur_cost_planning/tests/factories.py
src/waldur_cost_planning/tests/fixtures.py
src/waldur_cost_planning/tests/test_deployment_plans.py
src/waldur_cost_planning/tests/test_openstack_tenant.py