Metadata-Version: 2.1
Name: waldur-cost-planning
Version: 0.6.2
Summary: Waldur cost planning plugin allows to get a price estimate without actually creating the infrastructure.
Home-page: http://waldur.com
Author: OpenNode Team
Author-email: info@opennodecloud.com
License: MIT
Platform: UNKNOWN
Classifier: Framework :: Django
Classifier: Intended Audience :: Developers
Classifier: Intended Audience :: System Administrators
Classifier: Operating System :: OS Independent
Classifier: License :: OSI Approved :: MIT License
Provides-Extra: dev
